finlens/__init__.py
finlens/_core/__init__.py
finlens/_version.py
finlens/auth/__init__.py
finlens/auth/api_key.py
finlens/clients/__init__.py
finlens/clients/base.py
finlens/clients/eod/MarketEod.py
finlens/clients/eod/SectorEod.py
finlens/clients/eod/StockEod.py
finlens/clients/eod/__init__.py
finlens/clients/eod/helper.py
finlens/clients/eod/icb_types.py
finlens/clients/eod/investor/MarketInvestor.py
finlens/clients/eod/investor/SectorInvestor.py
finlens/clients/eod/investor/StockInvestor.py
finlens/clients/eod/investor/__init__.py
finlens/clients/eod/investor/investor.py
finlens/clients/eod_main.py
finlens/clients/financials.py
finlens/clients/index.py
finlens/clients/info.py
finlens/clients/intraday/DerivativeIntraday.py
finlens/clients/intraday/MarketIntraday.py
finlens/clients/intraday/StockIntraday.py
finlens/clients/intraday/__init__.py
finlens/clients/intraday/helper.py
finlens/clients/intraday_main.py
finlens/clients/reporting/__init__.py
finlens/clients/reporting/helper.py
finlens/clients/reporting/reporting_main.py
finlens/clients/reporting/types.py
finlens/config.py
finlens/exceptions.py
finlens/models/__init__.py
finlens/models/base.py
finlens/models/eod.py
finlens/models/financials.py
finlens/models/index.py
finlens/models/meta.py
finlens/py.typed
finlens/transport/__init__.py
finlens/transport/cache.py
finlens/transport/http.py
finlens/transport/rate_limiter.py
finlens/types.py
finlens/utils/__init__.py
finlens/utils/_validate_date_eod.py
finlens/utils/convert.py
finlens/utils/pagination.py
finlens/utils/time.py
finlens/validators.py
finlens-0.1.11.dist-info/METADATA
finlens-0.1.11.dist-info/RECORD
finlens-0.1.11.dist-info/WHEEL
finlens-0.1.11.dist-info/licenses/LICENSE
finlens-0.1.11.dist-info/top_level.txt
private_core/__init__.py
private_core/auth_core.cpython-310-darwin.so
private_core/cache_core.cpython-310-darwin.so
private_core/cache_mixin.cpython-310-darwin.so
private_core/cache_policy.cpython-310-darwin.so
private_core/eod_core.cpython-310-darwin.so
private_core/financials_core.cpython-310-darwin.so
private_core/helpers.cpython-310-darwin.so
