Metadata-Version: 2.4
Name: finlens
Version: 0.1.11
Summary: High-performance Python client for the FinLens financial data platform.
Author: FinLens Team
Project-URL: Homepage, https://finlens.vn
Project-URL: Documentation, https://finlens.vn/docs/finlenspy/
Keywords: finlens,finance,market-data,api-client,vietnam
Classifier: Development Status :: 3 - Alpha
Classifier: Intended Audience :: Developers
Classifier: Intended Audience :: Financial and Insurance Industry
Classifier: Operating System :: Microsoft :: Windows
Classifier: Operating System :: POSIX :: Linux
Classifier: Operating System :: MacOS
Classifier: Programming Language :: Python
Classifier: Programming Language :: Python :: 3
Classifier: Programming Language :: Python :: 3.10
Classifier: Programming Language :: Python :: 3.11
Classifier: Programming Language :: Python :: 3.12
Classifier: Programming Language :: Python :: 3.13
Classifier: Topic :: Office/Business :: Financial
Classifier: Topic :: Software Development :: Libraries
Requires-Python: >=3.10
Requires-Dist: pandas>=2.1.2
Requires-Dist: requests>=2.31.0
Requires-Dist: pydantic>=2.4.0
Provides-Extra: dev
Requires-Dist: pytest>=7.4; extra == "dev"
Requires-Dist: cibuildwheel>=2.17.0; extra == "dev"
Requires-Dist: twine>=5.0.0; extra == "dev"
Requires-Dist: python-dotenv>=1.0.0; extra == "dev"
